README.md
setup.py
labelci/__init__.py
labelci.egg-info/PKG-INFO
labelci.egg-info/SOURCES.txt
labelci.egg-info/dependency_links.txt
labelci.egg-info/entry_points.txt
labelci.egg-info/requires.txt
labelci.egg-info/top_level.txt
labelci/bin/__init__.py
labelci/bin/cli.py
labelci/bin/utils.py
labelci/common/__init__.py
labelci/common/credential.py
labelci/common/utils.py
labelci/common/exception/__init__.py
labelci/common/exception/labelci_sdk_exception.py
labelci/core/__init__.py
labelci/core/dataset.py
labelci/core/tensor.py
labelci/core/client/__init__.py
labelci/core/client/client.py
labelci/core/client/config.py
labelci/core/client/test_client.py
labelci/core/index/__init__.py
labelci/core/index/index.py